{
    "users": [
        {
            "id": 1,
            "nickname": "Hellscream",
            "name": "John",
            "last name": "Black",
            "password": "password01",
            "is admin": true,
            "age": 32
        },
        {
            "id": 2,
            "nickname": "Windrunner",
            "name": "Kate",
            "last name": "Smith",
            "password": "password02",
            "is admin": false,
            "age": 28
        },
        {
            "id": 3,
            "nickname": "Malfurion",
            "name": "Eddie",
            "last name": "Havoc",
            "password": "password03",
            "is admin": false,
            "age": 27
        },
        {
            "id": 4,
            "nickname": "Illidan",
            "name": "Malcolm",
            "last name": "Green",
            "password": "password04",
            "is admin": false,
            "age": 23
        }
    ]
}
